tvb/__init__.py
tvb/analyzers/__init__.py
tvb/analyzers/fft.py
tvb/analyzers/fmri_balloon.py
tvb/analyzers/graph.py
tvb/analyzers/ica.py
tvb/analyzers/ica_algorithm.py
tvb/analyzers/info.py
tvb/analyzers/metric_kuramoto_index.py
tvb/analyzers/metric_proxy_metastability.py
tvb/analyzers/metric_variance_global.py
tvb/analyzers/metric_variance_of_node_variance.py
tvb/analyzers/node_coherence.py
tvb/analyzers/node_complex_coherence.py
tvb/analyzers/pca.py
tvb/analyzers/wavelet.py
tvb/basic/__init__.py
tvb/basic/exceptions.py
tvb/basic/profile.py
tvb/basic/readers.py
tvb/basic/config/__init__.py
tvb/basic/config/environment.py
tvb/basic/config/profile_settings.py
tvb/basic/config/settings.py
tvb/basic/config/stored.py
tvb/basic/config/tvb.version
tvb/basic/config/utils.py
tvb/basic/logger/__init__.py
tvb/basic/logger/builder.py
tvb/basic/logger/library_logger.conf
tvb/basic/logger/library_logger_test.conf
tvb/basic/logger/simple_handler.py
tvb/basic/neotraits/__init__.py
tvb/basic/neotraits/_attr.py
tvb/basic/neotraits/_core.py
tvb/basic/neotraits/_declarative_base.py
tvb/basic/neotraits/api.py
tvb/basic/neotraits/ex.py
tvb/basic/neotraits/info.py
tvb/datatypes/__init__.py
tvb/datatypes/connectivity.py
tvb/datatypes/cortex.py
tvb/datatypes/equations.py
tvb/datatypes/fcd.py
tvb/datatypes/graph.py
tvb/datatypes/local_connectivity.py
tvb/datatypes/mode_decompositions.py
tvb/datatypes/patterns.py
tvb/datatypes/projections.py
tvb/datatypes/region_mapping.py
tvb/datatypes/sensors.py
tvb/datatypes/spectral.py
tvb/datatypes/structural.py
tvb/datatypes/surfaces.py
tvb/datatypes/temporal_correlations.py
tvb/datatypes/time_series.py
tvb/datatypes/tracts.py
tvb/datatypes/volumes.py
tvb/simulator/__init__.py
tvb/simulator/common.py
tvb/simulator/coupling.py
tvb/simulator/descriptors.py
tvb/simulator/history.py
tvb/simulator/integrators.py
tvb/simulator/lab.py
tvb/simulator/monitors.py
tvb/simulator/noise.py
tvb/simulator/simulator.py
tvb/simulator/_numba/__init__.py
tvb_library-2.9.2.dist-info/METADATA
tvb_library-2.9.2.dist-info/WHEEL
tvb_library-2.9.2.dist-info/licenses/AUTHORS
tvb_library-2.9.2.dist-info/licenses/LICENSE
tvb_library-2.9.2.dist-info/RECORD
