Metadata-Version: 2.4
Name: tvb-library
Version: 2.9.2
Summary: A package for performing whole brain simulations
Project-URL: Download, https://github.com/the-virtual-brain/tvb-root
Project-URL: Homepage, https://www.thevirtualbrain.org
Author: Marmaduke Woodman, Jan Fousek, Stuart Knock, Paula Sanz Leon, Viktor Jirsa
Maintainer-email: TVB Admin <tvb.admin@thevirtualbrain.org>
License: TheVirtualBrain is a brain-simulation software. See also http://www.thevirtualbrain.org
License-File: AUTHORS
License-File: LICENSE
Keywords: animal,brain,delay,dynamics,human,models,neuronal,neuroscience,simulator,tvb
Classifier: Development Status :: 6 - Mature
Classifier: Intended Audience :: Science/Research
Classifier: License :: OSI Approved :: GNU General Public License v3 or later (GPLv3+)
Classifier: Programming Language :: Python :: 3
Classifier: Programming Language :: Python :: 3.8
Classifier: Programming Language :: Python :: 3.9
Classifier: Programming Language :: Python :: 3.10
Classifier: Programming Language :: Python :: 3.11
Requires-Python: >=3.8
Requires-Dist: autopep8
Requires-Dist: deprecated
Requires-Dist: docutils
Requires-Dist: ipywidgets
Requires-Dist: mako>=1.1.4
Requires-Dist: matplotlib
Requires-Dist: networkx
Requires-Dist: numba
Requires-Dist: numexpr
Requires-Dist: numpy<2.0
Requires-Dist: scipy
Requires-Dist: six
Provides-Extra: test
Requires-Dist: h5py; extra == 'test'
Requires-Dist: pytest; extra == 'test'
Requires-Dist: pytest-benchmark; extra == 'test'
Requires-Dist: pytest-xdist; extra == 'test'
Requires-Dist: tvb-data; extra == 'test'
Requires-Dist: tvb-gdist; extra == 'test'
